.bumpversion.cfg
.cookiecutterrc
.coveragerc
.editorconfig
.travis.yml
AUTHORS.rst
CHANGELOG.rst
CONTRIBUTING.rst
LICENSE
MANIFEST.in
README.rst
appveyor.yml
setup.cfg
setup.py
tox.ini
ci/appveyor-bootstrap.py
ci/appveyor-download.py
ci/appveyor-with-compiler.cmd
ci/bootstrap.py
ci/templates/.travis.yml
ci/templates/appveyor.yml
docs/authors.rst
docs/changelog.rst
docs/conf.py
docs/contributing.rst
docs/index.rst
docs/installation.rst
docs/modules.rst
docs/orderbookmdp.order_book.rst
docs/orderbookmdp.rl.rst
docs/orderbookmdp.rst
docs/readme.rst
docs/requirements.txt
docs/spelling_wordlist.txt
docs/usage.rst
src/orderbookmdp/__init__.py
src/orderbookmdp/_orderbookmdp.pyx
src/orderbookmdp.egg-info/PKG-INFO
src/orderbookmdp.egg-info/SOURCES.txt
src/orderbookmdp.egg-info/dependency_links.txt
src/orderbookmdp.egg-info/not-zip-safe
src/orderbookmdp.egg-info/top_level.txt
src/orderbookmdp/order_book/__init__.py
src/orderbookmdp/order_book/constants.py
src/orderbookmdp/order_book/market.py
src/orderbookmdp/order_book/order_books.py
src/orderbookmdp/order_book/order_types.py
src/orderbookmdp/order_book/orderstream.py
src/orderbookmdp/order_book/price_level.py
src/orderbookmdp/order_book/price_levels.py
src/orderbookmdp/order_book/utils.py
src/orderbookmdp/rl/__init__.py
src/orderbookmdp/rl/abstract_envs.py
src/orderbookmdp/rl/app.py
src/orderbookmdp/rl/dist_envs.py
src/orderbookmdp/rl/env_utils.py
src/orderbookmdp/rl/ewma.py
src/orderbookmdp/rl/market_env.py
src/orderbookmdp/rl/market_order_envs.py
src/orderbookmdp/rl/multi_agent_envs.py
tests/test_externalMarket.py
tests/test_orderbookmdp.py
tests/testdata/beginning_level_3.json
tests/testdata/collectdata.py
tests/testdata/ending_level_3.json
tests/testdata/messages.json